peateazea/__init__.py
peateazea/protocols/__init__.py
peateazea/protocols/avkans.py
peateazea/protocols/base.py
peateazea/protocols/visca.py
peateazea/protocols/visca_udp.py
peateazea-0.1.1.dist-info/LICENSE
peateazea-0.1.1.dist-info/METADATA
peateazea-0.1.1.dist-info/WHEEL
peateazea-0.1.1.dist-info/top_level.txt
peateazea-0.1.1.dist-info/RECORD
