Metadata-Version: 2.1
Name: peateazea
Version: 0.1.1
Summary: A Python package for controlling PTZ cameras through various protocols
Home-page: https://github.com/benbaptist/peateazea
Author: Ben Baptist
Author-email: sawham6@gmail.com
License: UNKNOWN
Platform: UNKNOWN
Classifier: Programming Language :: Python :: 3
Classifier: License :: OSI Approved :: MIT License
Classifier: Operating System :: OS Independent
Requires-Python: >=3.9
License-File: LICENSE
Requires-Dist: requests
